[
  {
    "nome": "Aula 1",
    "data": "2023-10-26",
    "hora": "19:00"
  },
  {
    "nome": "Aula 2",
    "data": "2023-10-27",
    "hora": "19:00"
  },
  {
    "nome": "Aula 3",
    "data": "2023-10-28",
    "hora": "19:00"
  },
  {
    "nome": "Aula 4",
    "data": "2023-10-29",
    "hora": "19:00"
  },
  {
    "nome": "Aula 5",
    "data": "2023-10-30",
    "hora": "19:00"
  },
  {
    "nome": "Aula 6",
    "data": "2023-10-31",
    "hora": "19:00"
  },
  {
    "nome": "Aula 7",
    "data": "2023-11-01",
    "hora": "19:00"
  },
  {
    "nome": "Aula 8",
    "data": "2023-11-02",
    "hora": "19:00"
  },
  {
    "nome": "Aula 9",
    "data": "2023-11-03",
    "hora": "19:00"
  },
  {
    "nome": "Aula 10",
    "data": "2023-11-04",
    "hora": "19:00"
  },
  {
    "nome": "Aula 11",
    "data": "2023-11-05",
    "hora": "19:00"
  },
  {
    "nome": "Aula 12",
    "data": "2023-11-06",
    "hora": "19:00"
  },
  {
    "nome": "Aula 13",
    "data": "2023-11-07",
    "hora": "19:00"
  },
  {
    "nome": "Aula 14",
    "data": "2023-11-08",
    "hora": "19:00"
  },
  {
    "nome": "Aula 15",
    "data": "2023-11-09",
    "hora": "19:00"
  },
  {
    "nome": "Aula 16",
    "data": "2023-11-10",
    "hora": "19:00"
  },
  {
    "nome": "Aula 32",
    "data": "2023-11-26",
    "hora": "19:00"
  },
  {
    "nome": "Aula 33",
    "data": "2023-11-27",
    "hora": "19:00"
  },
  {
    "nome": "Aula 34",
    "data": "2023-11-28",
    "hora": "19:00"
  },
  {
    "nome": "Aula 35",
    "data": "2024-01-22",
    "hora": "19:00"
  },
  {
    "nome": "Aula 36",
    "data": "2024-01-30",
    "hora": "19:00"
  },
  {
    "nome": "Aula 36",
    "data": "2022-08-15",
    "hora": "19:00"
  },
  {
    "nome": "Aula 36",
    "data": "2022-09-15",
    "hora": "19:00"
  },
  {
    "nome": "Aula 36",
    "data": "2022-10-15",
    "hora": "19:00"
  },
  {
    "nome": "Aula 36",
    "data": "2022-11-29",
    "hora": "19:00"
  }
]
